langchain_tool_client/__init__.py
langchain_tool_client-0.0.3.dist-info/METADATA
langchain_tool_client-0.0.3.dist-info/WHEEL
langchain_tool_client-0.0.3.dist-info/RECORD
