Metadata-Version: 2.4
Name: langchain-tool-client
Version: 0.0.3
Summary: LangChain Tool Client SDK (Python)
Project-URL: repository, https://github.com/langchain-ai/langchain-tool-server
Requires-Python: >=3.10
Requires-Dist: httpx>=0.22.1
Requires-Dist: langchain-core>=0.3.0
Requires-Dist: orjson>=3.10.1
